gitProjTool/__init__.py
gitProjTool/projTool.py
gitProjTool-0.0.2.dist-info/LICENSE
gitProjTool-0.0.2.dist-info/METADATA
gitProjTool-0.0.2.dist-info/WHEEL
gitProjTool-0.0.2.dist-info/entry_points.txt
gitProjTool-0.0.2.dist-info/top_level.txt
gitProjTool-0.0.2.dist-info/RECORD
