Metadata-Version: 2.1
Name: gitProjTool
Version: 0.0.2
Summary: a tool that analyse project on git
Home-page: https://github.com/Onion-Shen/GitProjectTool
Author: Onion-Shen
Author-email: 18513385631@163.com
License: UNKNOWN
Platform: UNKNOWN
Classifier: Programming Language :: Python :: 3
Classifier: License :: OSI Approved :: GNU General Public License v3 (GPLv3)
Classifier: Operating System :: MacOS
Requires-Dist: prettytable
